fuzzer-cov/__init__.py
fuzzer-cov/__main__.py
fuzzer_cov/__init__.py
fuzzer_cov/__main__.py
fuzzer_cov/commands/__init__.py
fuzzer_cov/commands/libfuzzer.py
fuzzer_cov/core/__init__.py
fuzzer_cov/core/container.py
fuzzer_cov/core/executor.py
fuzzer_cov/core/logger.py
fuzzer_cov/core/utils.py
fuzzer_cov/executor/__init__.py
fuzzer_cov/executor/libfuzzer.py
fuzzer_cov/platform/__init__.py
fuzzer_cov/platform/executor.py
fuzzer_cov/platform/genhtml.py
fuzzer_cov/platform/lcov.py
fuzzer_cov-0.2.1.dist-info/LICENSE
fuzzer_cov-0.2.1.dist-info/METADATA
fuzzer_cov-0.2.1.dist-info/WHEEL
fuzzer_cov-0.2.1.dist-info/top_level.txt
fuzzer_cov-0.2.1.dist-info/RECORD
