Metadata-Version: 2.1
Name: fuzzer-cov
Version: 0.2.1
Summary: UNKNOWN
Home-page: https://github.com/Myriad-Dreamin/fuzzer-cov
Author: Myriad Dreamin
Author-email: camiyoru@gmail.com
License: MIT
Download-URL: https://github.com/Myriad-Dreamin/fuzzer-cov/archive/v0.2.1.tar.gz
Platform: UNKNOWN
Classifier: Development Status :: 4 - Beta
Classifier: Intended Audience :: Developers
Classifier: Topic :: Software Development
Classifier: License :: OSI Approved :: MIT License
Classifier: Operating System :: OS Independent
Classifier: Programming Language :: Python :: 3.6
